<?xml version='1.0' encoding='UTF-8'?>
<types:mule xmlns:types="http://www.mulesoft.org/schema/mule/types">
  <types:catalog>
    <types:type name="auto_4a57814b-01c7-4dd2-8719-46dee0b6683d_Output-Variables-x" format="java">
      <types:shape format="raml" autogeneratedOrigin="b96b4cf3-2d91-49ee-ba54-fedb8b241b24"><![CDATA[#%RAML 1.0 DataType
type: string]]></types:shape>
    </types:type>
    <types:type name="auto_4a57814b-01c7-4dd2-8719-46dee0b6683d_Output-Attributes" format="java">
      <types:shape format="weave" example="weave/autogenerated/4a57814b-01c7-4dd2-8719-46dee0b6683d/Output-Attributes.wev" autogeneratedOrigin="b96b4cf3-2d91-49ee-ba54-fedb8b241b24"><![CDATA[%dw 2.0

type auto_4a57814b_01c7_4dd2_8719_46dee0b6683d_Output_Attributes = {|
  listenerPath: String, 
  rawRequestPath: String, 
  relativePath: String, 
  maskedRequestPath: String, 
  version: String, 
  scheme: String, 
  method: String, 
  requestUri: String, 
  rawRequestUri: String, 
  queryString: String, 
  localAddress: String, 
  remoteAddress: String, 
  clientCertificate?: java_security_cert_Certificate, 
  queryParams: { _?: String }, 
  uriParams: { _?: String }, 
  requestPath: String, 
  headers: { _?: String }
|} {"typeAlias": "HttpRequestAttributes",
"typeId": "org.mule.extension.http.api.HttpRequestAttributes"}
type java_security_cert_Certificate = {|
  encoded?: Binary, 
  publicKey?: java_security_PublicKey, 
  "type"?: String
|} {"typeAlias": "Certificate",
"typeId": "java.security.cert.Certificate"}
type java_security_PublicKey = {|  |} {"typeAlias": "PublicKey",
"typeId": "java.security.PublicKey"}





]]></types:shape>
    </types:type>
    <types:type name="auto_4a57814b-01c7-4dd2-8719-46dee0b6683d_Output-Payload" format="java">
      <types:shape format="weave" example="weave/autogenerated/4a57814b-01c7-4dd2-8719-46dee0b6683d/Output-Payload.wev" autogeneratedOrigin="b96b4cf3-2d91-49ee-ba54-fedb8b241b24"><![CDATA[%dw 2.0

type auto_4a57814b_01c7_4dd2_8719_46dee0b6683d_Output_Payload = Any

]]></types:shape>
    </types:type>
    <types:type name="auto_4a57814b-01c7-4dd2-8719-46dee0b6683d_Input-Attributes" format="java">
      <types:shape format="weave" example="weave/autogenerated/4a57814b-01c7-4dd2-8719-46dee0b6683d/Input-Attributes.wev" autogeneratedOrigin="b96b4cf3-2d91-49ee-ba54-fedb8b241b24"><![CDATA[%dw 2.0

type auto_4a57814b_01c7_4dd2_8719_46dee0b6683d_Input_Attributes = {|
  listenerPath: String, 
  rawRequestPath: String, 
  relativePath: String, 
  maskedRequestPath: String, 
  version: String, 
  scheme: String, 
  method: String, 
  requestUri: String, 
  rawRequestUri: String, 
  queryString: String, 
  localAddress: String, 
  remoteAddress: String, 
  clientCertificate?: java_security_cert_Certificate, 
  queryParams: { _?: String }, 
  uriParams: { _?: String }, 
  requestPath: String, 
  headers: { _?: String }
|} {"typeAlias": "HttpRequestAttributes",
"typeId": "org.mule.extension.http.api.HttpRequestAttributes"}
type java_security_cert_Certificate = {|
  encoded?: Binary, 
  publicKey?: java_security_PublicKey, 
  "type"?: String
|} {"typeAlias": "Certificate",
"typeId": "java.security.cert.Certificate"}
type java_security_PublicKey = {|  |} {"typeAlias": "PublicKey",
"typeId": "java.security.PublicKey"}





]]></types:shape>
    </types:type>
    <types:type name="auto_4a57814b-01c7-4dd2-8719-46dee0b6683d_Input-Variables-x" format="java">
      <types:shape format="raml" autogeneratedOrigin="b96b4cf3-2d91-49ee-ba54-fedb8b241b24"><![CDATA[#%RAML 1.0 DataType
type: string]]></types:shape>
    </types:type>
    <types:type name="auto_4a57814b-01c7-4dd2-8719-46dee0b6683d_Input-Payload" format="java">
      <types:shape format="raml" autogeneratedOrigin="b96b4cf3-2d91-49ee-ba54-fedb8b241b24"><![CDATA[#%RAML 1.0 DataType
type: string]]></types:shape>
    </types:type>
  </types:catalog>
  <types:enrichment select="#4a57814b-01c7-4dd2-8719-46dee0b6683d">
    <types:processor-declaration>
      <types:input-event>
        <types:message>
          <types:payload type="auto_4a57814b-01c7-4dd2-8719-46dee0b6683d_Input-Payload"/>
          <types:attributes type="auto_4a57814b-01c7-4dd2-8719-46dee0b6683d_Input-Attributes"/>
        </types:message>
        <types:variables>
          <types:variable name="x" type="auto_4a57814b-01c7-4dd2-8719-46dee0b6683d_Input-Variables-x"/>
        </types:variables>
      </types:input-event>
      <types:output-event>
        <types:message>
          <types:payload type="auto_4a57814b-01c7-4dd2-8719-46dee0b6683d_Output-Payload"/>
          <types:attributes type="auto_4a57814b-01c7-4dd2-8719-46dee0b6683d_Output-Attributes"/>
        </types:message>
        <types:variables>
          <types:variable name="x" type="auto_4a57814b-01c7-4dd2-8719-46dee0b6683d_Output-Variables-x"/>
        </types:variables>
      </types:output-event>
    </types:processor-declaration>
  </types:enrichment>
</types:mule>